mboot2/__init__.py
mboot2/__main__.py
mboot2/commands.py
mboot2/connection/__init__.py
mboot2/connection/base.py
mboot2/connection/uart.py
mboot2/connection/usb.py
mboot2/errorcodes.py
mboot2/exceptions.py
mboot2/mcuboot.py
mboot2/memories.py
mboot2/properties.py
mboot2-0.3.5.dist-info/entry_points.txt
mboot2-0.3.5.dist-info/LICENSE
mboot2-0.3.5.dist-info/WHEEL
mboot2-0.3.5.dist-info/METADATA
mboot2-0.3.5.dist-info/RECORD
