Metadata-Version: 2.1
Name: mboot2
Version: 0.3.5
Summary: Python tool and library for interacting with NXP MCUBoot devices.
Home-page: https://github.com/conorpp/pyMBoot
License: BSD-3-Clause
Author: Martin Olejar,
Author-email: martin.olejar@gmail.com
Requires-Python: >=3.6
Classifier: Environment :: Console
Classifier: License :: OSI Approved :: BSD License
Classifier: Operating System :: Microsoft :: Windows
Classifier: Operating System :: POSIX :: Linux
Classifier: Programming Language :: Python :: 3
Classifier: Programming Language :: Python :: 3.6
Classifier: Programming Language :: Python :: 3.7
Classifier: Programming Language :: Python :: 3.8
Classifier: Programming Language :: Python :: 3.9
Classifier: Topic :: Scientific/Engineering
Classifier: Topic :: Software Development :: Embedded Systems
Classifier: Topic :: Utilities
Requires-Dist: bincopy (==17.9.0)
Requires-Dist: click (==7.0)
Requires-Dist: easy_enum (==0.3.0)
Requires-Dist: fido2 (==0.8.1)
Requires-Dist: pyserial (==3.4)
Project-URL: Repository, https://github.com/conorpp/pyMBoot
